vimdoc/VERSION.txt
vimdoc/__init__.py
vimdoc/__main__.py
vimdoc/_shtab.py
vimdoc/args.py
vimdoc/block.py
vimdoc/codeline.py
vimdoc/docline.py
vimdoc/error.py
vimdoc/module.py
vimdoc/output.py
vimdoc/paragraph.py
vimdoc/parser.py
vimdoc/regex.py
vimdoc-0.7.1.data/scripts/vimdoc
vimdoc-0.7.1.dist-info/LICENSE
vimdoc-0.7.1.dist-info/METADATA
vimdoc-0.7.1.dist-info/WHEEL
vimdoc-0.7.1.dist-info/top_level.txt
vimdoc-0.7.1.dist-info/RECORD
