Metadata-Version: 2.1
Name: vimdoc
Version: 0.7.1
Summary: Generate vim helpfiles
Author-email: Nate Soares <nate@so8r.es>
License: Apache 2.0
Project-URL: Repository, https://github.com/google/vimdoc
Classifier: Development Status :: 3 - Alpha
Classifier: License :: OSI Approved :: Apache Software License
Classifier: Programming Language :: Python :: 3
Classifier: Programming Language :: Python :: 3.4
Classifier: Topic :: Software Development :: Documentation
Requires-Python: >=3.4
License-File: LICENSE
Provides-Extra: completion
Requires-Dist: shtab ; extra == 'completion'
